gias3.mesh-3.0.1-py3.11-nspkg.pth
gias3/mesh/__init__.py
gias3/mesh/csgtools.py
gias3/mesh/inp.py
gias3/mesh/plywriter.py
gias3/mesh/simplemesh.py
gias3/mesh/smutils.py
gias3/mesh/tetgenoutput.py
gias3/mesh/vtkPolydataReader.py
gias3/mesh/vtktools.py
gias3_mesh-3.0.1.dist-info/LICENSE
gias3_mesh-3.0.1.dist-info/METADATA
gias3_mesh-3.0.1.dist-info/WHEEL
gias3_mesh-3.0.1.dist-info/namespace_packages.txt
gias3_mesh-3.0.1.dist-info/top_level.txt
gias3_mesh-3.0.1.dist-info/RECORD
